README
setup.py
sham/__init__.py
sham.egg-info/PKG-INFO
sham.egg-info/SOURCES.txt
sham.egg-info/dependency_links.txt
sham.egg-info/top_level.txt
sham/machine/__init__.py
sham/network/__init__.py
sham/network/interfaces.py
sham/storage/__init__.py
sham/storage/pools.py
sham/storage/volumes.py