Metadata-Version: 1.0
Name: sham
Version: 0.1.0
Summary: Friendly interface to libvirt
Home-page: https://github.com/rossdylan/sham
Author: Ross Delinger
Author-email: ross.delinger@gmail.com
License: UNKNOWN
Platform: UNKNOWN
